monday_lib/__init__.py
monday_lib/monday_api_library.py
monday_lib-1.1.dist-info/METADATA
monday_lib-1.1.dist-info/WHEEL
monday_lib-1.1.dist-info/licenses/LICENSE.txt
monday_lib-1.1.dist-info/RECORD
