Metadata-Version: 2.1
Name: monday_lib
Version: 1.1
Summary: A wrapper for monday.com API
Project-URL: Homepage, https://github.com/Frodothedwarf/monday_lib
Project-URL: Bug Tracker, https://github.com/Frodothedwarf/monday_lib/issues
Author-email: Frederich Pedersen <frodo@hobbits.dk>
License-File: LICENSE.txt
Classifier: License :: OSI Approved :: GNU General Public License v3 (GPLv3)
Classifier: Operating System :: OS Independent
Classifier: Programming Language :: Python :: 3
Requires-Python: >=3.7
